wrangleai/__init__.py
wrangleai/client.py
wrangleai/types.py
wrangleai-0.2.0.dist-info/licenses/LICENSE
wrangleai-0.2.0.dist-info/METADATA
wrangleai-0.2.0.dist-info/WHEEL
wrangleai-0.2.0.dist-info/top_level.txt
wrangleai-0.2.0.dist-info/RECORD
