Metadata-Version: 2.4
Name: wrangleai
Version: 0.2.0
Summary: Official Python client for Wrangle AI. OpenAI-compatible smart routing and cost tracking.
Author-email: Wrangle AI <support@wrangleai.com>
License: MIT
Project-URL: Homepage, https://wrangleai.com
Keywords: wrangleai,openai,ai,llm,smart-routing
Classifier: Programming Language :: Python :: 3
Classifier: License :: OSI Approved :: MIT License
Classifier: Operating System :: OS Independent
Requires-Python: >=3.8
License-File: LICENSE
Requires-Dist: httpx>=0.27.0
Dynamic: license-file
